Workbook

Sheet Assumptions
A1: PROJECT SITARA - MODEL ASSUMPTIONS (blue = editable; yellow = highest-impact levers)
A3: Label | B3: Value | C3: Unit | D3: Type | E3: Source / logic
A4: FX rate (INR per USD) | B4: 90 | C4: Rs/$ | D4: Assumption | E4: Management estimate, Jul-2026
A5: GST rate (India plans) | B5: 0.18 | C5: % | D5: Fact | E5: India prices GST-inclusive; revenue modelled net of GST; NRI = zero-rated export
A6: Blended net subscription ARPU (Rs/mo) | B6: 815 | C6: Rs/mo | D6: Mgmt estimate | E6: Derived on Pricing sheet from plan mix; net of GST
A7: Add-on ARPU (consult minutes, reports) (Rs/mo) | B7: 65 | C7: Rs/mo | D7: Assumption | E7: ~8% attach; benchmark: AstroTalk session spend Rs500-1500 (Entrackr FY24)
A8: Monthly churn - base | B8: 0.06 | C8: %/mo | D8: Benchmark+assumption | E8: Recurly DTC benchmark 6.5%/mo; annual-mix damping; VALIDATION TARGET
A9: Monthly churn - conservative | B9: 0.075 | C9: %/mo | D9: Scenario | E9: +25% stress
A10: Monthly churn - aggressive | B10: 0.045 | C10: %/mo | D10: Scenario | E10: Only if cohorts prove it
A11: Blended CAC - base (Rs) | B11: 3600 | C11: Rs | D11: Benchmark+assumption | E11: AstroTalk domestic Rs575-870 (Entrackr); NRI premium assumed 4-5x
A12: CAC - conservative (Rs) | B12: 4500 | C12: Rs | D12: Scenario | E12: +25% stress
A13: CAC - aggressive (Rs) | B13: 3000 | C13: Rs | D13: Scenario | E13: Referral/organic mix matures
A14: Referral share of new customers | B14: 0.12 | C14: % | D14: Assumption | E14: Family-chart gifting loop
A15: Refund rate (% of gross revenue) | B15: 0.025 | C15: % | D15: Assumption | E15: 30-day money-back guarantee
... A25: Churn floor - base (%/mo) | B25: 0.05 | C25: %/mo | D25: Assumption | E25: Best-case mature churn, base case
A27: All downstream sheets recalculate from this sheet. Every figure in the board decks traces here.

Sheet Pricing
A1: PRICING ARCHITECTURE (effective monthly ARPU, net of GST)
A3: Plan | B3: Customer | C3: Monthly | D3: Annual | E3: Mix % | F3: Gross eff Rs/mo | G3: GST factor | H3: Net eff Rs/mo | I3: Weighted Rs/mo
A4: NRI Standard | B4: NRI individual (US/UK/CA/Gulf) | C4: $12.99 | D4: $99 | E4: 0.45 | F4: =(0.4*12.99+0.6*99/12)*Assumptions!$B$4 -> 913.14 | G4: 1 | H4: =F4*G4 -> 913.14 | I4: =H4*E4 -> 410.913
A5: NRI Premium | B5: NRI premium; 30 consult-min/qtr | C5: $24.99 | D5: $199 | E5: 0.12 | F5: =(0.4*24.99+0.6*199/12)*Assumptions!$B$4 -> 1795.14 | G5: 1 | H5: =F5*G5 -> 1795.14 | I5: =H5*E5 -> 215.4168
A6: India Aarambh | B6: Metro India individual | C6: Rs499 | D6: Rs3,999 | E6: 0.3 | F6: =0.4*499+0.6*3999/12 -> 399.55 | G6: =1/(1+Assumptions!$B$5) -> 0.84745763 | H6: =F6*G6 -> 338.60169 | I6: =H6*E6 -> 101.58051
A7: India Pragati | B7: Metro India premium; 15 min/qtr | C7: Rs999 | D7: Rs7,999 | E7: 0.13 | F7: =0.4*999+0.6*7999/12 -> 799.55 | G7: =1/(1+Assumptions!$B$5) -> 0.84745763 | H7: =F7*G7 -> 677.58475 | I7: =H7*E7 -> 88.086017
A9: Blended net subscription ARPU (Rs/mo) - computed | I9: =SUM(I4:I7) -> 815.99633
A10: Value used by model (Assumptions!B6) - keep aligned: | I10: =Assumptions!$B$6 -> 815
A12: Assumes 60% of subscribers on annual billing (40% monthly). Mix percentages are management estimates.

Sheet Customer Growth
A1: CUSTOMER GROWTH - 36 MONTHS, BASE CASE (opening + new - churned = closing)
A3: Month | B3: Marketing Rs | C3: CAC Rs | D3: New (funnel) | E3: Referrals | F3: Founding | G3: Total new | H3: Opening | I3: Churn rate | J3: Churned | K3: Closing | L3: Annual subs | M3: Premium subs
A4: 1 | B4: 300000 | C4: =Assumptions!$B$11 -> 3600 | D4: =B4/C4 -> 83.333333 | E4: =D4*Assumptions!$B$14 -> 10 | F4: =IF(A4=4,Assumptions!$B$23,0) -> 0 | G4: =D4+E4+F4 -> 93.333333 | H4: 0 | I4: =MAX(Assumptions!$B$25,Assumptions!$B$8-MAX(0,A4-12)*Assumptions!$B$24) -> 0.06 | J4: =H4*I4 -> 0 | K4: =H4+G4-J4 -> 93.333333 | L4: =K4*Assumptions!$B$21 -> 56 | M4: =K4*Assumptions!$B$22 -> 23.333333
A5: 2 | B5: 300000 | C5: =Assumptions!$B$11 -> 3600 | D5: =B5/C5 -> 83.333333 | E5: =D5*Assumptions!$B$14 -> 10 | F5: =IF(A5=4,Assumptions!$B$23,0) -> 0 | G5: =D5+E5+F5 -> 93.333333 | H5: =K4 -> 93.333333 | I5: =MAX(Assumptions!$B$25,Assumptions!$B$8-MAX(0,A5-12)*Assumptions!$B$24) -> 0.06 | J5: =H5*I5 -> 5.6 | K5: =H5+G5-J5 -> 181.06667 | L5: =K5*Assumptions!$B$21 -> 108.64 | M5: =K5*Assumptions!$B$22 -> 45.266667
A6: 3 | B6: 300000 | C6: =Assumptions!$B$11 -> 3600 | D6: =B6/C6 -> 83.333333 | E6: =D6*Assumptions!$B$14 -> 10 | F6: =IF(A6=4,Assumptions!$B$23,0) -> 0 | G6: =D6+E6+F6 -> 93.333333 | H6: =K5 -> 181.06667 | I6: =MAX(Assumptions!$B$25,Assumptions!$B$8-MAX(0,A6-12)*Assumptions!$B$24) -> 0.06 | J6: =H6*I6 -> 10.864 | K6: =H6+G6-J6 -> 263.536 | L6: =K6*Assumptions!$B$21 -> 158.1216 | M6: =K6*Assumptions!$B$22 -> 65.884
A7: 4 | B7: 800000 | C7: =Assumptions!$B$11 -> 3600 | D7: =B7/C7 -> 222.22222 | E7: =D7*Assumptions!$B$14 -> 26.666667 | F7: =IF(A7=4,Assumptions!$B$23,0) -> 300 | G7: =D7+E7+F7 -> 548.88889 | H7: =K6 -> 263.536 | I7: =MAX(Assumptions!$B$25,Assumptions!$B$8-MAX(0,A7-12)*Assumptions!$B$24) -> 0.06 | J7: =H7*I7 -> 15.81216 | K7: =H7+G7-J7 -> 796.61273 | L7: =K7*Assumptions!$B$21 -> 477.96764 | M7: =K7*Assumptions!$B$22 -> 199.15318
A8: 5 | B8: 800000 | C8: =Assumptions!$B$11 -> 3600 | D8: =B8/C8 -> 222.22222 | E8: =D8*Assumptions!$B$14 -> 26.666667 | F8: =IF(A8=4,Assumptions!$B$23,0) -> 0 | G8: =D8+E8+F8 -> 248.88889 | H8: =K7 -> 796.61273 | I8: =MAX(Assumptions!$B$25,Assumptions!$B$8-MAX(0,A8-12)*Assumptions!$B$24) -> 0.06 | J8: =H8*I8 -> 47.796764 | K8: =H8+G8-J8 -> 997.70485 | L8: =K8*Assumptions!$B$21 -> 598.62291 | M8: =K8*Assumptions!$B$22 -> 249.42621
A9: 6 | B9: 800000 | C9: =Assumptions!$B$11 -> 3600 | D9: =B9/C9 -> 222.22222 | E9: =D9*Assumptions!$B$14 -> 26.666667 | F9: =IF(A9=4,Assumptions!$B$23,0) -> 0 | G9: =D9+E9+F9 -> 248.88889 | H9: =K8 -> 997.70485 | I9: =MAX(Assumptions!$B$25,Assumptions!$B$8-MAX(0,A9-12)*Assumptions!$B$24) -> 0.06 | J9: =H9*I9 -> 59.862291 | K9: =H9+G9-J9 -> 1186.7315 | L9: =K9*Assumptions!$B$21 -> 712.03887 | M9: =K9*Assumptions!$B$22 -> 296.68286
A10: 7 | B10: 1500000 | C10: =Assumptions!$B$11 -> 3600 | D10: =B10/C10 -> 416.66667 | E10: =D10*Assumptions!$B$14 -> 50 | F10: =IF(A10=4,Assumptions!$B$23,0) -> 0 | G10: =D10+E10+F10 -> 466.66667 | H10: =K9 -> 1186.7315 | I10: =MAX(Assumptions!$B$25,Assumptions!$B$8-MAX(0,A10-12)*Assumptions!$B$24) -> 0.06 | J10: =H10*I10 -> 71.203887 | K10: =H10+G10-J10 -> 1582.1942 | L10: =K10*Assumptions!$B$21 -> 949.31654 | M10: =K10*Assumptions!$B$22 -> 395.54856
A11: 8 | B11: 1500000 | C11: =Assumptions!$B$11 -> 3600 | D11: =B11/C11 -> 416.66667 | E11: =D11*Assumptions!$B$14 -> 50 | F11: =IF(A11=4,Assumptions!$B$23,0) -> 0 | G11: =D11+E11+F11 -> 466.66667 | H11: =K10 -> 1582.1942 | I11: =MAX(Assumptions!$B$25,Assumptions!$B$8-MAX(0,A11-12)*Assumptions!$B$24) -> 0.06 | J11: =H11*I11 -> 94.931654 | K11: =H11+G11-J11 -> 1953.9292 | L11: =K11*Assumptions!$B$21 -> 1172.3575 | M11: =K11*Assumptions!$B$22 -> 488.48231
A12: 9 | B12: 1500000 | C12: =Assumptions!$B$11 -> 3600 | D12: =B12/C12 -> 416.66667 | E12: =D12*Assumptions!$B$14 -> 50 | F12: =IF(A12=4,Assumptions!$B$23,0) -> 0 | G12: =D12+E12+F12 -> 466.66667 | H12: =K11 -> 1953.9292 | I12: =MAX(Assumptions!$B$25,Assumptions!$B$8-MAX(0,A12-12)*Assumptions!$B$24) -> 0.06 | J12: =H12*I12 -> 117.23575 | K12: =H12+G12-J12 -> 2303.3602 | L12: =K12*Assumptions!$B$21 -> 1382.0161 | M12: =K12*Assumptions!$B$22 -> 575.84004
A13: 10 | B13: 1500000 | C13: =Assumptions!$B$11 -> 3600 | D13: =B13/C13 -> 416.66667 | E13: =D13*Assumptions!$B$14 -> 50 | F13: =IF(A13=4,Assumptions!$B$23,0) -> 0 | G13: =D13+E13+F13 -> 466.66667 | H13: =K12 -> 2303.3602 | I13: =MAX(Assumptions!$B$25,Assumptions!$B$8-MAX(0,A13-12)*Assumptions!$B$24) -> 0.06 | J13: =H13*I13 -> 138.20161 | K13: =H13+G13-J13 -> 2631.8252 | L13: =K13*Assumptions!$B$21 -> 1579.0951 | M13: =K13*Assumptions!$B$22 -> 657.9563
A14: 11 | B14: 1500000 | C14: =Assumptions!$B$11 -> 3600 | D14: =B14/C14 -> 416.66667 | E14: =D14*Assumptions!$B$14 -> 50 | F14: =IF(A14=4,Assumptions!$B$23,0) -> 0 | G14: =D14+E14+F14 -> 466.66667 | H14: =K13 -> 2631.8252 | I14: =MAX(Assumptions!$B$25,Assumptions!$B$8-MAX(0,A14-12)*Assumptions!$B$24) -> 0.06 | J14: =H14*I14 -> 157.90951 | K14: =H14+G14-J14 -> 2940.5824 | L14: =K14*Assumptions!$B$21 -> 1764.3494 | M14: =K14*Assumptions!$B$22 -> 735.14559
A15: 12 | B15: 1500000 | C15: =Assumptions!$B$11 -> 3600 | D15: =B15/C15 -> 416.66667 | E15: =D15*Assumptions!$B$14 -> 50 | F15: =IF(A15=4,Assumptions!$B$23,0) -> 0 | G15: =D15+E15+F15 -> 466.66667 | H15: =K14 -> 2940.5824 | I15: =MAX(Assumptions!$B$25,Assumptions!$B$8-MAX(0,A15-12)*Assumptions!$B$24) -> 0.06 | J15: =H15*I15 -> 176.43494 | K15: =H15+G15-J15 -> 3230.8141 | L15: =K15*Assumptions!$B$21 -> 1938.4885 | M15: =K15*Assumptions!$B$22 -> 807.70352
A16: 13 | B16: 2500000 | C16: =Assumptions!$B$11 -> 3600 | D16: =B16/C16 -> 694.44444 | E16: =D16*Assumptions!$B$14 -> 83.333333 | F16: =IF(A16=4,Assumptions!$B$23,0) -> 0 | G16: =D16+E16+F16 -> 777.77778 | H16: =K15 -> 3230.8141 | I16: =MAX(Assumptions!$B$25,Assumptions!$B$8-MAX(0,A16-12)*Assumptions!$B$24) -> 0.0595 | J16: =H16*I16 -> 192.23344 | K16: =H16+G16-J16 -> 3816.3584 | L16: =K16*Assumptions!$B$21 -> 2289.8151 | M16: =K16*Assumptions!$B$22 -> 954.08961
... A39: 36 | B39: 3500000 | C39: =Assumptions!$B$11 -> 3600 | D39: =B39/C39 -> 972.22222 | E39: =D39*Assumptions!$B$14 -> 116.66667 | F39: =IF(A39=4,Assumptions!$B$23,0) -> 0 | G39: =D39+E39+F39 -> 1088.8889 | H39: =K38 -> 14162.992 | I39: =MAX(Assumptions!$B$25,Assumptions!$B$8-MAX(0,A39-12)*Assumptions!$B$24) -> 0.05 | J39: =H39*I39 -> 708.14958 | K39: =H39+G39-J39 -> 14543.731 | L39: =K39*Assumptions!$B$21 -> 8726.2386 | M39: =K39*Assumptions!$B$22 -> 3635.9327
A41: Milestones: | B41: M6 | C41: =K9 -> 1186.7315 | D41: M12 | E41: =K15 -> 3230.8141 | F41: M24 | G41: =K27 -> 8551.5852 | H41: M36 | I41: =K39 -> 14543.731

Sheet Funnel
A1: ACQUISITION FUNNEL - representative steady month (M12)
A3: Stage | B3: Conversion | C3: Volume /mo | D3: Cost Rs | E3: Logic (type)
A4: Ad impressions | B4: - | C4: =C6/0.03/0.08 -> 694444.44 | E4: Implied at 8% impression-to-visit x CTR mix (assumption)
A5: Site visitors | B5: - | C5: =C6/0.03 -> 55555.556 | E5: Visitor-to-trial 3% (management estimate)
A6: Trials / Honest-Kundli signups | B6: 3.0% of visitors | C6: =C7/0.25 -> 1666.6667 | E6: Trial-to-paid 25% (management estimate)
A7: New paid customers | B7: 25% of trials | C7: ='Customer Growth'!D15 -> 416.66667 | D7: ='Customer Growth'!B15 -> 1500000 | E7: Funnel spend M12
A8: Referral additions | B8: 12% of funnel | C8: ='Customer Growth'!E15 -> 50 | E8: Family-chart gift loop (assumption)
A9: Effective blended CAC | B9: - | D9: ='Customer Growth'!B15/('Customer Growth'!D15+'Customer Growth'!E15) -> 3214.2857 | E9: Marketing / all new
A11: Funnel rates are management estimates until replaced by Gate-1 cohort actuals.

Sheet Revenue
A1: REVENUE - 36 MONTHS (Rs, recognised monthly, net of GST)
A3: Month | B3: Avg subscribers | C3: Subscription rev | D3: Add-on rev | E3: Gross rev | F3: Refunds | G3: Net revenue | H3: Deferred-cash memo
A4: 1 | B4: =('Customer Growth'!H4+'Customer Growth'!K4)/2 -> 46.666667 | C4: =B4*Assumptions!$B$6 -> 38033.333 | D4: =B4*Assumptions!$B$7 -> 3033.3333 | E4: =C4+D4 -> 41066.667 | F4: =E4*Assumptions!$B$15 -> 1026.6667 | G4: =E4-F4 -> 40040 | H4: ='Customer Growth'!G4*Assumptions!$B$21*Assumptions!$B$6*5.5 -> 251020
A5: 2 | B5: =('Customer Growth'!H5+'Customer Growth'!K5)/2 -> 137.2 | C5: =B5*Assumptions!$B$6 -> 111818 | D5: =B5*Assumptions!$B$7 -> 8918 | E5: =C5+D5 -> 120736 | F5: =E5*Assumptions!$B$15 -> 3018.4 | G5: =E5-F5 -> 117717.6 | H5: ='Customer Growth'!G5*Assumptions!$B$21*Assumptions!$B$6*5.5 -> 251020
A6: 3 | B6: =('Customer Growth'!H6+'Customer Growth'!K6)/2 -> 222.30133 | C6: =B6*Assumptions!$B$6 -> 181175.59 | D6: =B6*Assumptions!$B$7 -> 14449.587 | E6: =C6+D6 -> 195625.17 | F6: =E6*Assumptions!$B$15 -> 4890.6293 | G6: =E6-F6 -> 190734.54 | H6: ='Customer Growth'!G6*Assumptions!$B$21*Assumptions!$B$6*5.5 -> 251020
A7: 4 | B7: =('Customer Growth'!H7+'Customer Growth'!K7)/2 -> 530.07436 | C7: =B7*Assumptions!$B$6 -> 432010.61 | D7: =B7*Assumptions!$B$7 -> 34454.834 | E7: =C7+D7 -> 466465.44 | F7: =E7*Assumptions!$B$15 -> 11661.636 | G7: =E7-F7 -> 454803.8 | H7: ='Customer Growth'!G7*Assumptions!$B$21*Assumptions!$B$6*5.5 -> 1476236.7
A8: 5 | B8: =('Customer Growth'!H8+'Customer Growth'!K8)/2 -> 897.15879 | C8: =B8*Assumptions!$B$6 -> 731184.42 | D8: =B8*Assumptions!$B$7 -> 58315.321 | E8: =C8+D8 -> 789499.74 | F8: =E8*Assumptions!$B$15 -> 19737.493 | G8: =E8-F8 -> 769762.24 | H8: ='Customer Growth'!G8*Assumptions!$B$21*Assumptions!$B$6*5.5 -> 669386.67
A9: 6 | B9: =('Customer Growth'!H9+'Customer Growth'!K9)/2 -> 1092.2182 | C9: =B9*Assumptions!$B$6 -> 890157.79 | D9: =B9*Assumptions!$B$7 -> 70994.18 | E9: =C9+D9 -> 961151.97 | F9: =E9*Assumptions!$B$15 -> 24028.799 | G9: =E9-F9 -> 937123.18 | H9: ='Customer Growth'!G9*Assumptions!$B$21*Assumptions!$B$6*5.5 -> 669386.67
A10: 7 | B10: =('Customer Growth'!H10+'Customer Growth'!K10)/2 -> 1384.4628 | C10: =B10*Assumptions!$B$6 -> 1128337.2 | D10: =B10*Assumptions!$B$7 -> 89990.085 | E10: =C10+D10 -> 1218327.3 | F10: =E10*Assumptions!$B$15 -> 30458.183 | G10: =E10-F10 -> 1187869.1 | H10: ='Customer Growth'!G10*Assumptions!$B$21*Assumptions!$B$6*5.5 -> 1255100
A11: 8 | B11: =('Customer Growth'!H11+'Customer Growth'!K11)/2 -> 1768.0617 | C11: =B11*Assumptions!$B$6 -> 1440970.3 | D11: =B11*Assumptions!$B$7 -> 114924.01 | E11: =C11+D11 -> 1555894.3 | F11: =E11*Assumptions!$B$15 -> 38897.358 | G11: =E11-F11 -> 1516997 | H11: ='Customer Growth'!G11*Assumptions!$B$21*Assumptions!$B$6*5.5 -> 1255100
A12: 9 | B12: =('Customer Growth'!H12+'Customer Growth'!K12)/2 -> 2128.6447 | C12: =B12*Assumptions!$B$6 -> 1734845.4 | D12: =B12*Assumptions!$B$7 -> 138361.91 | E12: =C12+D12 -> 1873207.3 | F12: =E12*Assumptions!$B$15 -> 46830.183 | G12: =E12-F12 -> 1826377.2 | H12: ='Customer Growth'!G12*Assumptions!$B$21*Assumptions!$B$6*5.5 -> 1255100
A13: 10 | B13: =('Customer Growth'!H13+'Customer Growth'!K13)/2 -> 2467.5927 | C13: =B13*Assumptions!$B$6 -> 2011088 | D13: =B13*Assumptions!$B$7 -> 160393.52 | E13: =C13+D13 -> 2171481.6 | F13: =E13*Assumptions!$B$15 -> 54287.039 | G13: =E13-F13 -> 2117194.5 | H13: ='Customer Growth'!G13*Assumptions!$B$21*Assumptions!$B$6*5.5 -> 1255100
A14: 11 | B14: =('Customer Growth'!H14+'Customer Growth'!K14)/2 -> 2786.2038 | C14: =B14*Assumptions!$B$6 -> 2270756.1 | D14: =B14*Assumptions!$B$7 -> 181103.25 | E14: =C14+D14 -> 2451859.3 | F14: =E14*Assumptions!$B$15 -> 61296.483 | G14: =E14-F14 -> 2390562.9 | H14: ='Customer Growth'!G14*Assumptions!$B$21*Assumptions!$B$6*5.5 -> 1255100
A15: 12 | B15: =('Customer Growth'!H15+'Customer Growth'!K15)/2 -> 3085.6982 | C15: =B15*Assumptions!$B$6 -> 2514844.1 | D15: =B15*Assumptions!$B$7 -> 200570.38 | E15: =C15+D15 -> 2715414.4 | F15: =E15*Assumptions!$B$15 -> 67885.361 | G15: =E15-F15 -> 2647529.1 | H15: ='Customer Growth'!G15*Assumptions!$B$21*Assumptions!$B$6*5.5 -> 1255100
... A39: 36 | B39: =('Customer Growth'!H39+'Customer Growth'!K39)/2 -> 14353.361 | C39: =B39*Assumptions!$B$6 -> 11697989 | D39: =B39*Assumptions!$B$7 -> 932968.48 | E39: =C39+D39 -> 12630958 | F39: =E39*Assumptions!$B$15 -> 315773.95 | G39: =E39-F39 -> 12315184 | H39: ='Customer Growth'!G39*Assumptions!$B$21*Assumptions!$B$6*5.5 -> 2928566.7
A41: Year totals: | B41: Y1 | C41: =SUM(G4:G15) -> 14196711 | D41: Y2 | E41: =SUM(G16:G27) -> 63435374 | F41: Y3 | G41: =SUM(G28:G39) -> 1.2162814e+08
A42: Deferred-cash memo: annual plans collect ~5.5 months of revenue ahead of recognition on average.

Sheet Cost of Revenue
A1: COST OF REVENUE - 36 MONTHS (Rs)
A3: Month | B3: AI cost | C3: Human minutes | D3: Support | E3: Infra | F3: Payment fees | G3: Total COGS | H3: Gross profit | I3: GM %
A4: 1 | B4: =Revenue!B4*Assumptions!$B$16 -> 3266.6667 | C4: =Revenue!B4*Assumptions!$B$17 -> 2100 | D4: =Revenue!B4*Assumptions!$B$18 -> 1166.6667 | E4: =Revenue!B4*Assumptions!$B$20 -> 700 | F4: =Revenue!E4*Assumptions!$B$19 -> 1149.8667 | G4: =SUM(B4:F4) -> 8383.2 | H4: =Revenue!G4-G4 -> 31656.8 | I4: =IF(Revenue!G4=0,0,H4/Revenue!G4) -> 0.79062937
A5: 2 | B5: =Revenue!B5*Assumptions!$B$16 -> 9604 | C5: =Revenue!B5*Assumptions!$B$17 -> 6174 | D5: =Revenue!B5*Assumptions!$B$18 -> 3430 | E5: =Revenue!B5*Assumptions!$B$20 -> 2058 | F5: =Revenue!E5*Assumptions!$B$19 -> 3380.608 | G5: =SUM(B5:F5) -> 24646.608 | H5: =Revenue!G5-G5 -> 93070.992 | I5: =IF(Revenue!G5=0,0,H5/Revenue!G5) -> 0.79062937
A6: 3 | B6: =Revenue!B6*Assumptions!$B$16 -> 15561.093 | C6: =Revenue!B6*Assumptions!$B$17 -> 10003.56 | D6: =Revenue!B6*Assumptions!$B$18 -> 5557.5333 | E6: =Revenue!B6*Assumptions!$B$20 -> 3334.52 | F6: =Revenue!E6*Assumptions!$B$19 -> 5477.5049 | G6: =SUM(B6:F6) -> 39934.212 | H6: =Revenue!G6-G6 -> 150800.33 | I6: =IF(Revenue!G6=0,0,H6/Revenue!G6) -> 0.79062937
A7: 4 | B7: =Revenue!B7*Assumptions!$B$16 -> 37105.206 | C7: =Revenue!B7*Assumptions!$B$17 -> 23853.346 | D7: =Revenue!B7*Assumptions!$B$18 -> 13251.859 | E7: =Revenue!B7*Assumptions!$B$20 -> 7951.1155 | F7: =Revenue!E7*Assumptions!$B$19 -> 13061.032 | G7: =SUM(B7:F7) -> 95222.559 | H7: =Revenue!G7-G7 -> 359581.25 | I7: =IF(Revenue!G7=0,0,H7/Revenue!G7) -> 0.79062937
A8: 5 | B8: =Revenue!B8*Assumptions!$B$16 -> 62801.115 | C8: =Revenue!B8*Assumptions!$B$17 -> 40372.146 | D8: =Revenue!B8*Assumptions!$B$18 -> 22428.97 | E8: =Revenue!B8*Assumptions!$B$20 -> 13457.382 | F8: =Revenue!E8*Assumptions!$B$19 -> 22105.993 | G8: =SUM(B8:F8) -> 161165.61 | H8: =Revenue!G8-G8 -> 608596.64 | I8: =IF(Revenue!G8=0,0,H8/Revenue!G8) -> 0.79062937
A9: 6 | B9: =Revenue!B9*Assumptions!$B$16 -> 76455.271 | C9: =Revenue!B9*Assumptions!$B$17 -> 49149.817 | D9: =Revenue!B9*Assumptions!$B$18 -> 27305.454 | E9: =Revenue!B9*Assumptions!$B$20 -> 16383.272 | F9: =Revenue!E9*Assumptions!$B$19 -> 26912.255 | G9: =SUM(B9:F9) -> 196206.07 | H9: =Revenue!G9-G9 -> 740917.11 | I9: =IF(Revenue!G9=0,0,H9/Revenue!G9) -> 0.79062937
A10: 7 | B10: =Revenue!B10*Assumptions!$B$16 -> 96912.399 | C10: =Revenue!B10*Assumptions!$B$17 -> 62300.828 | D10: =Revenue!B10*Assumptions!$B$18 -> 34611.571 | E10: =Revenue!B10*Assumptions!$B$20 -> 20766.943 | F10: =Revenue!E10*Assumptions!$B$19 -> 34113.164 | G10: =SUM(B10:F10) -> 248704.9 | H10: =Revenue!G10-G10 -> 939164.21 | I10: =IF(Revenue!G10=0,0,H10/Revenue!G10) -> 0.79062937
A11: 8 | B11: =Revenue!B11*Assumptions!$B$16 -> 123764.32 | C11: =Revenue!B11*Assumptions!$B$17 -> 79562.778 | D11: =Revenue!B11*Assumptions!$B$18 -> 44201.543 | E11: =Revenue!B11*Assumptions!$B$20 -> 26520.926 | F11: =Revenue!E11*Assumptions!$B$19 -> 43565.041 | G11: =SUM(B11:F11) -> 317614.61 | H11: =Revenue!G11-G11 -> 1199382.4 | I11: =IF(Revenue!G11=0,0,H11/Revenue!G11) -> 0.79062937
A12: 9 | B12: =Revenue!B12*Assumptions!$B$16 -> 149005.13 | C12: =Revenue!B12*Assumptions!$B$17 -> 95789.012 | D12: =Revenue!B12*Assumptions!$B$18 -> 53216.118 | E12: =Revenue!B12*Assumptions!$B$20 -> 31929.671 | F12: =Revenue!E12*Assumptions!$B$19 -> 52449.805 | G12: =SUM(B12:F12) -> 382389.73 | H12: =Revenue!G12-G12 -> 1443987.4 | I12: =IF(Revenue!G12=0,0,H12/Revenue!G12) -> 0.79062937
A13: 10 | B13: =Revenue!B13*Assumptions!$B$16 -> 172731.49 | C13: =Revenue!B13*Assumptions!$B$17 -> 111041.67 | D13: =Revenue!B13*Assumptions!$B$18 -> 61689.817 | E13: =Revenue!B13*Assumptions!$B$20 -> 37013.89 | F13: =Revenue!E13*Assumptions!$B$19 -> 60801.484 | G13: =SUM(B13:F13) -> 443278.35 | H13: =Revenue!G13-G13 -> 1673916.2 | I13: =IF(Revenue!G13=0,0,H13/Revenue!G13) -> 0.79062937
A14: 11 | B14: =Revenue!B14*Assumptions!$B$16 -> 195034.27 | C14: =Revenue!B14*Assumptions!$B$17 -> 125379.17 | D14: =Revenue!B14*Assumptions!$B$18 -> 69655.095 | E14: =Revenue!B14*Assumptions!$B$20 -> 41793.057 | F14: =Revenue!E14*Assumptions!$B$19 -> 68652.061 | G14: =SUM(B14:F14) -> 500513.65 | H14: =Revenue!G14-G14 -> 1890049.2 | I14: =IF(Revenue!G14=0,0,H14/Revenue!G14) -> 0.79062937
A15: 12 | B15: =Revenue!B15*Assumptions!$B$16 -> 215998.88 | C15: =Revenue!B15*Assumptions!$B$17 -> 138856.42 | D15: =Revenue!B15*Assumptions!$B$18 -> 77142.456 | E15: =Revenue!B15*Assumptions!$B$20 -> 46285.473 | F15: =Revenue!E15*Assumptions!$B$19 -> 76031.604 | G15: =SUM(B15:F15) -> 554314.83 | H15: =Revenue!G15-G15 -> 2093214.3 | I15: =IF(Revenue!G15=0,0,H15/Revenue!G15) -> 0.79062937
... A39: 36 | B39: =Revenue!B39*Assumptions!$B$16 -> 1004735.3 | C39: =Revenue!B39*Assumptions!$B$17 -> 645901.26 | D39: =Revenue!B39*Assumptions!$B$18 -> 358834.03 | E39: =Revenue!B39*Assumptions!$B$20 -> 215300.42 | F39: =Revenue!E39*Assumptions!$B$19 -> 353666.82 | G39: =SUM(B39:F39) -> 2578437.8 | H39: =Revenue!G39-G39 -> 9736746.1 | I39: =IF(Revenue!G39=0,0,H39/Revenue!G39) -> 0.79062937
A41: Y totals GP: | B41: =SUM(H4:H15) -> 11224337 | C41: =SUM(H16:H27) -> 50153870 | D41: =SUM(H28:H39) -> 96162780

Sheet Headcount
A1: HEADCOUNT PLAN (fully-loaded monthly cost, Rs)
A3: Role | B3: Phase A (M1-6) | C3: Phase B (M7-18) | D3: Phase C (M19-36) | E3: Monthly cost Rs | F3: Notes
A4: Founder/CEO | B4: 1 | C4: 1 | D4: 1 | E4: 250000 | F4: Below-market; corrected at Series A
A5: Founding engineers | B5: 2 | C5: 3 | D5: 5 | E5: 300000 | F5: Per-engineer avg Rs3.0L loaded
A6: Jyotish lead (part-time then full) | B6: 0.5 | C6: 1 | D6: 1 | E6: 250000 | F6: Credibility-critical hire
A7: Designer (contract) | B7: 0.5 | C7: 1 | D7: 1 | E7: 180000
A8: Growth/marketing | B8: 0 | C8: 1 | D8: 2 | E8: 220000
A9: Content/community | B9: 0 | C9: 1 | D9: 2 | E9: 150000
A10: Astrologer-panel ops | B10: 0 | C10: 0.5 | D10: 1 | E10: 140000
A11: Support | B11: 0 | C11: 1 | D11: 3 | E11: 80000
A12: Finance/admin (fractional) | B12: 0.2 | C12: 0.4 | D12: 1 | E12: 120000
A13: Monthly salary bill | B13: =SUMPRODUCT(B4:B12,$E$4:$E$12) -> 1089000 | C13: =SUMPRODUCT(C4:C12,$E$4:$E$12) -> 2148000 | D13: =SUMPRODUCT(D4:D12,$E$4:$E$12) -> 3420000
A15: Headcount (FTE) | B15: =SUM(B4:B12) -> 4.2 | C15: =SUM(C4:C12) -> 9.9 | D15: =SUM(D4:D12) -> 17

Sheet Marketing
A1: MARKETING - CHANNEL CAC AND SPEND
A3: Channel | B3: CAC Rs | C3: Spend share | D3: Weighted CAC | E3: Type
A4: Meta (IG/FB) diaspora | B4: 4200 | C4: 0.4 | D4: =B4*C4 -> 1680 | E4: Benchmark-derived
A5: Google search intent | B5: 4800 | C5: 0.15 | D5: =B5*C5 -> 720 | E5: Assumption
A6: Micro-influencer astrologers | B6: 3000 | C6: 0.15 | D6: =B6*C6 -> 450 | E6: Assumption
A7: Community/organic (Reddit, SEO) | B7: 1200 | C7: 0.12 | D7: =B7*C7 -> 144 | E7: Assumption
A8: Referral (family-chart gift) | B8: 800 | C8: 0.1 | D8: =B8*C8 -> 80 | E8: Cost of incentive
A9: Festival campaigns | B9: 3400 | C9: 0.08 | D9: =B9*C9 -> 272 | E9: Assumption
A10: Blended CAC (check vs Assumptions!B11) | D10: =SUM(D4:D9) -> 3346 | E10: =Assumptions!$B$11 -> 3600
A12: Monthly marketing spend schedule lives in 'Customer Growth' column B (editable).
A13: Benchmark: AstroTalk domestic CAC Rs575-870, 6-8 month recovery (Entrackr/growthx FY24-25).

Sheet Operating Expenses
A1: OPERATING EXPENSES + MONTHLY EBITDA ENGINE (Rs)
A3: Month | B3: Salaries | C3: Marketing | D3: Tech/software | E3: G&A/legal/office | F3: Other/contingency | G3: Total opex | H3: Net revenue | I3: Gross profit | J3: EBITDA
A4: 1 | B4: =IF(A4<=6,Headcount!$B$13,IF(A4<=18,Headcount!$C$13,Headcount!$D$13)) -> 1089000 | C4: ='Customer Growth'!B4 -> 300000 | D4: =IF(A4<=6,120000,IF(A4<=18,200000,320000)) -> 120000 | E4: =IF(A4<=6,150000,IF(A4<=18,250000,400000)) -> 150000 | F4: =0.05*(B4+D4+E4) -> 67950 | G4: =SUM(B4:F4) -> 1726950 | H4: =Revenue!G4 -> 40040 | I4: ='Cost of Revenue'!H4 -> 31656.8 | J4: =I4-G4 -> -1695293.2
A5: 2 | B5: =IF(A5<=6,Headcount!$B$13,IF(A5<=18,Headcount!$C$13,Headcount!$D$13)) -> 1089000 | C5: ='Customer Growth'!B5 -> 300000 | D5: =IF(A5<=6,120000,IF(A5<=18,200000,320000)) -> 120000 | E5: =IF(A5<=6,150000,IF(A5<=18,250000,400000)) -> 150000 | F5: =0.05*(B5+D5+E5) -> 67950 | G5: =SUM(B5:F5) -> 1726950 | H5: =Revenue!G5 -> 117717.6 | I5: ='Cost of Revenue'!H5 -> 93070.992 | J5: =I5-G5 -> -1633879
A6: 3 | B6: =IF(A6<=6,Headcount!$B$13,IF(A6<=18,Headcount!$C$13,Headcount!$D$13)) -> 1089000 | C6: ='Customer Growth'!B6 -> 300000 | D6: =IF(A6<=6,120000,IF(A6<=18,200000,320000)) -> 120000 | E6: =IF(A6<=6,150000,IF(A6<=18,250000,400000)) -> 150000 | F6: =0.05*(B6+D6+E6) -> 67950 | G6: =SUM(B6:F6) -> 1726950 | H6: =Revenue!G6 -> 190734.54 | I6: ='Cost of Revenue'!H6 -> 150800.33 | J6: =I6-G6 -> -1576149.7
A7: 4 | B7: =IF(A7<=6,Headcount!$B$13,IF(A7<=18,Headcount!$C$13,Headcount!$D$13)) -> 1089000 | C7: ='Customer Growth'!B7 -> 800000 | D7: =IF(A7<=6,120000,IF(A7<=18,200000,320000)) -> 120000 | E7: =IF(A7<=6,150000,IF(A7<=18,250000,400000)) -> 150000 | F7: =0.05*(B7+D7+E7) -> 67950 | G7: =SUM(B7:F7) -> 2226950 | H7: =Revenue!G7 -> 454803.8 | I7: ='Cost of Revenue'!H7 -> 359581.25 | J7: =I7-G7 -> -1867368.8
A8: 5 | B8: =IF(A8<=6,Headcount!$B$13,IF(A8<=18,Headcount!$C$13,Headcount!$D$13)) -> 1089000 | C8: ='Customer Growth'!B8 -> 800000 | D8: =IF(A8<=6,120000,IF(A8<=18,200000,320000)) -> 120000 | E8: =IF(A8<=6,150000,IF(A8<=18,250000,400000)) -> 150000 | F8: =0.05*(B8+D8+E8) -> 67950 | G8: =SUM(B8:F8) -> 2226950 | H8: =Revenue!G8 -> 769762.24 | I8: ='Cost of Revenue'!H8 -> 608596.64 | J8: =I8-G8 -> -1618353.4
A9: 6 | B9: =IF(A9<=6,Headcount!$B$13,IF(A9<=18,Headcount!$C$13,Headcount!$D$13)) -> 1089000 | C9: ='Customer Growth'!B9 -> 800000 | D9: =IF(A9<=6,120000,IF(A9<=18,200000,320000)) -> 120000 | E9: =IF(A9<=6,150000,IF(A9<=18,250000,400000)) -> 150000 | F9: =0.05*(B9+D9+E9) -> 67950 | G9: =SUM(B9:F9) -> 2226950 | H9: =Revenue!G9 -> 937123.18 | I9: ='Cost of Revenue'!H9 -> 740917.11 | J9: =I9-G9 -> -1486032.9
A10: 7 | B10: =IF(A10<=6,Headcount!$B$13,IF(A10<=18,Headcount!$C$13,Headcount!$D$13)) -> 2148000 | C10: ='Customer Growth'!B10 -> 1500000 | D10: =IF(A10<=6,120000,IF(A10<=18,200000,320000)) -> 200000 | E10: =IF(A10<=6,150000,IF(A10<=18,250000,400000)) -> 250000 | F10: =0.05*(B10+D10+E10) -> 129900 | G10: =SUM(B10:F10) -> 4227900 | H10: =Revenue!G10 -> 1187869.1 | I10: ='Cost of Revenue'!H10 -> 939164.21 | J10: =I10-G10 -> -3288735.8
A11: 8 | B11: =IF(A11<=6,Headcount!$B$13,IF(A11<=18,Headcount!$C$13,Headcount!$D$13)) -> 2148000 | C11: ='Customer Growth'!B11 -> 1500000 | D11: =IF(A11<=6,120000,IF(A11<=18,200000,320000)) -> 200000 | E11: =IF(A11<=6,150000,IF(A11<=18,250000,400000)) -> 250000 | F11: =0.05*(B11+D11+E11) -> 129900 | G11: =SUM(B11:F11) -> 4227900 | H11: =Revenue!G11 -> 1516997 | I11: ='Cost of Revenue'!H11 -> 1199382.4 | J11: =I11-G11 -> -3028517.6
A12: 9 | B12: =IF(A12<=6,Headcount!$B$13,IF(A12<=18,Headcount!$C$13,Headcount!$D$13)) -> 2148000 | C12: ='Customer Growth'!B12 -> 1500000 | D12: =IF(A12<=6,120000,IF(A12<=18,200000,320000)) -> 200000 | E12: =IF(A12<=6,150000,IF(A12<=18,250000,400000)) -> 250000 | F12: =0.05*(B12+D12+E12) -> 129900 | G12: =SUM(B12:F12) -> 4227900 | H12: =Revenue!G12 -> 1826377.2 | I12: ='Cost of Revenue'!H12 -> 1443987.4 | J12: =I12-G12 -> -2783912.6
A13: 10 | B13: =IF(A13<=6,Headcount!$B$13,IF(A13<=18,Headcount!$C$13,Headcount!$D$13)) -> 2148000 | C13: ='Customer Growth'!B13 -> 1500000 | D13: =IF(A13<=6,120000,IF(A13<=18,200000,320000)) -> 200000 | E13: =IF(A13<=6,150000,IF(A13<=18,250000,400000)) -> 250000 | F13: =0.05*(B13+D13+E13) -> 129900 | G13: =SUM(B13:F13) -> 4227900 | H13: =Revenue!G13 -> 2117194.5 | I13: ='Cost of Revenue'!H13 -> 1673916.2 | J13: =I13-G13 -> -2553983.8
A14: 11 | B14: =IF(A14<=6,Headcount!$B$13,IF(A14<=18,Headcount!$C$13,Headcount!$D$13)) -> 2148000 | C14: ='Customer Growth'!B14 -> 1500000 | D14: =IF(A14<=6,120000,IF(A14<=18,200000,320000)) -> 200000 | E14: =IF(A14<=6,150000,IF(A14<=18,250000,400000)) -> 250000 | F14: =0.05*(B14+D14+E14) -> 129900 | G14: =SUM(B14:F14) -> 4227900 | H14: =Revenue!G14 -> 2390562.9 | I14: ='Cost of Revenue'!H14 -> 1890049.2 | J14: =I14-G14 -> -2337850.8
A15: 12 | B15: =IF(A15<=6,Headcount!$B$13,IF(A15<=18,Headcount!$C$13,Headcount!$D$13)) -> 2148000 | C15: ='Customer Growth'!B15 -> 1500000 | D15: =IF(A15<=6,120000,IF(A15<=18,200000,320000)) -> 200000 | E15: =IF(A15<=6,150000,IF(A15<=18,250000,400000)) -> 250000 | F15: =0.05*(B15+D15+E15) -> 129900 | G15: =SUM(B15:F15) -> 4227900 | H15: =Revenue!G15 -> 2647529.1 | I15: ='Cost of Revenue'!H15 -> 2093214.3 | J15: =I15-G15 -> -2134685.7
... A39: 36 | B39: =IF(A39<=6,Headcount!$B$13,IF(A39<=18,Headcount!$C$13,Headcount!$D$13)) -> 3420000 | C39: ='Customer Growth'!B39 -> 3500000 | D39: =IF(A39<=6,120000,IF(A39<=18,200000,320000)) -> 320000 | E39: =IF(A39<=6,150000,IF(A39<=18,250000,400000)) -> 400000 | F39: =0.05*(B39+D39+E39) -> 207000 | G39: =SUM(B39:F39) -> 7847000 | H39: =Revenue!G39 -> 12315184 | I39: ='Cost of Revenue'!H39 -> 9736746.1 | J39: =I39-G39 -> 1889746.1
A41: Y totals EBITDA: | B41: =SUM(J4:J15) -> -26004763 | C41: =SUM(J16:J27) -> -22295530 | D41: =SUM(J28:J39) -> 1998779.6
A42: Tech/G&A steps are management estimates. Contingency 5% of non-marketing opex.

Sheet P&L
A1: P&L - MONTHLY YEAR 1, ANNUAL Y1-Y3 (Rs)
A3: Line | B3: M1 | C3: M2 | D3: M3 | E3: M4 | F3: M5 | G3: M6 | H3: M7 | I3: M8 | J3: M9 | K3: M10 | L3: M11 | M3: M12 | N3: Year 1 | O3: Year 2 | P3: Year 3
A4: Subscription revenue | B4: =Revenue!C4 -> 38033.333 | C4: =Revenue!C5 -> 111818 | D4: =Revenue!C6 -> 181175.59 | E4: =Revenue!C7 -> 432010.61 | F4: =Revenue!C8 -> 731184.42 | G4: =Revenue!C9 -> 890157.79 | H4: =Revenue!C10 -> 1128337.2 | I4: =Revenue!C11 -> 1440970.3 | J4: =Revenue!C12 -> 1734845.4 | K4: =Revenue!C13 -> 2011088 | L4: =Revenue!C14 -> 2270756.1 | M4: =Revenue!C15 -> 2514844.1 | N4: =SUM(Revenue!C4:C15) -> 13485221 | O4: =SUM(Revenue!C16:C27) -> 60256212 | P4: =SUM(Revenue!C28:C39) -> 1.1553256e+08
A5: Add-on revenue | B5: =Revenue!D4 -> 3033.3333 | C5: =Revenue!D5 -> 8918 | D5: =Revenue!D6 -> 14449.587 | E5: =Revenue!D7 -> 34454.834 | F5: =Revenue!D8 -> 58315.321 | G5: =Revenue!D9 -> 70994.18 | H5: =Revenue!D10 -> 89990.085 | I5: =Revenue!D11 -> 114924.01 | J5: =Revenue!D12 -> 138361.91 | K5: =Revenue!D13 -> 160393.52 | L5: =Revenue!D14 -> 181103.25 | M5: =Revenue!D15 -> 200570.38 | N5: =SUM(Revenue!D4:D15) -> 1075508.4 | O5: =SUM(Revenue!D16:D27) -> 4805710.2 | P5: =SUM(Revenue!D28:D39) -> 9214253
A6: Refunds | B6: =-Revenue!F4 -> -1026.6667 | C6: =-Revenue!F5 -> -3018.4 | D6: =-Revenue!F6 -> -4890.6293 | E6: =-Revenue!F7 -> -11661.636 | F6: =-Revenue!F8 -> -19737.493 | G6: =-Revenue!F9 -> -24028.799 | H6: =-Revenue!F10 -> -30458.183 | I6: =-Revenue!F11 -> -38897.358 | J6: =-Revenue!F12 -> -46830.183 | K6: =-Revenue!F13 -> -54287.039 | L6: =-Revenue!F14 -> -61296.483 | M6: =-Revenue!F15 -> -67885.361 | N6: =-SUM(Revenue!F4:F15) -> -364018.23 | O6: =-SUM(Revenue!F16:F27) -> -1626548.1 | P6: =-SUM(Revenue!F28:F39) -> -3118670.3
A7: Net revenue | B7: =Revenue!G4 -> 40040 | C7: =Revenue!G5 -> 117717.6 | D7: =Revenue!G6 -> 190734.54 | E7: =Revenue!G7 -> 454803.8 | F7: =Revenue!G8 -> 769762.24 | G7: =Revenue!G9 -> 937123.18 | H7: =Revenue!G10 -> 1187869.1 | I7: =Revenue!G11 -> 1516997 | J7: =Revenue!G12 -> 1826377.2 | K7: =Revenue!G13 -> 2117194.5 | L7: =Revenue!G14 -> 2390562.9 | M7: =Revenue!G15 -> 2647529.1 | N7: =SUM(Revenue!G4:G15) -> 14196711 | O7: =SUM(Revenue!G16:G27) -> 63435374 | P7: =SUM(Revenue!G28:G39) -> 1.2162814e+08
A8: AI + infra cost | B8: =-('Cost of Revenue'!B4+'Cost of Revenue'!E4) -> -3966.6667 | C8: =-('Cost of Revenue'!B5+'Cost of Revenue'!E5) -> -11662 | D8: =-('Cost of Revenue'!B6+'Cost of Revenue'!E6) -> -18895.613 | E8: =-('Cost of Revenue'!B7+'Cost of Revenue'!E7) -> -45056.321 | F8: =-('Cost of Revenue'!B8+'Cost of Revenue'!E8) -> -76258.497 | G8: =-('Cost of Revenue'!B9+'Cost of Revenue'!E9) -> -92838.543 | H8: =-('Cost of Revenue'!B10+'Cost of Revenue'!E10) -> -117679.34 | I8: =-('Cost of Revenue'!B11+'Cost of Revenue'!E11) -> -150285.25 | J8: =-('Cost of Revenue'!B12+'Cost of Revenue'!E12) -> -180934.8 | K8: =-('Cost of Revenue'!B13+'Cost of Revenue'!E13) -> -209745.38 | L8: =-('Cost of Revenue'!B14+'Cost of Revenue'!E14) -> -236827.32 | M8: =-('Cost of Revenue'!B15+'Cost of Revenue'!E15) -> -262284.35 | N8: =-SUM('Cost of Revenue'!B4:B15)-SUM('Cost of Revenue'!E4:E15) -> -1406434.1 | O8: =-SUM('Cost of Revenue'!B16:B27)-SUM('Cost of Revenue'!E16:E27) -> -6284390.2 | P8: =-SUM('Cost of Revenue'!B28:B39)-SUM('Cost of Revenue'!E28:E39) -> -12049408
A9: Human review / consult cost | B9: =-'Cost of Revenue'!C4 -> -2100 | C9: =-'Cost of Revenue'!C5 -> -6174 | D9: =-'Cost of Revenue'!C6 -> -10003.56 | E9: =-'Cost of Revenue'!C7 -> -23853.346 | F9: =-'Cost of Revenue'!C8 -> -40372.146 | G9: =-'Cost of Revenue'!C9 -> -49149.817 | H9: =-'Cost of Revenue'!C10 -> -62300.828 | I9: =-'Cost of Revenue'!C11 -> -79562.778 | J9: =-'Cost of Revenue'!C12 -> -95789.012 | K9: =-'Cost of Revenue'!C13 -> -111041.67 | L9: =-'Cost of Revenue'!C14 -> -125379.17 | M9: =-'Cost of Revenue'!C15 -> -138856.42 | N9: =-SUM('Cost of Revenue'!C4:C15) -> -744582.75 | O9: =-SUM('Cost of Revenue'!C16:C27) -> -3327030.1 | P9: =-SUM('Cost of Revenue'!C28:C39) -> -6379098.2
A10: Support cost | B10: =-'Cost of Revenue'!D4 -> -1166.6667 | C10: =-'Cost of Revenue'!D5 -> -3430 | D10: =-'Cost of Revenue'!D6 -> -5557.5333 | E10: =-'Cost of Revenue'!D7 -> -13251.859 | F10: =-'Cost of Revenue'!D8 -> -22428.97 | G10: =-'Cost of Revenue'!D9 -> -27305.454 | H10: =-'Cost of Revenue'!D10 -> -34611.571 | I10: =-'Cost of Revenue'!D11 -> -44201.543 | J10: =-'Cost of Revenue'!D12 -> -53216.118 | K10: =-'Cost of Revenue'!D13 -> -61689.817 | L10: =-'Cost of Revenue'!D14 -> -69655.095 | M10: =-'Cost of Revenue'!D15 -> -77142.456 | N10: =-SUM('Cost of Revenue'!D4:D15) -> -413657.08 | O10: =-SUM('Cost of Revenue'!D16:D27) -> -1848350.1 | P10: =-SUM('Cost of Revenue'!D28:D39) -> -3543943.5
A11: Payment fees | B11: =-'Cost of Revenue'!F4 -> -1149.8667 | C11: =-'Cost of Revenue'!F5 -> -3380.608 | D11: =-'Cost of Revenue'!F6 -> -5477.5049 | E11: =-'Cost of Revenue'!F7 -> -13061.032 | F11: =-'Cost of Revenue'!F8 -> -22105.993 | G11: =-'Cost of Revenue'!F9 -> -26912.255 | H11: =-'Cost of Revenue'!F10 -> -34113.164 | I11: =-'Cost of Revenue'!F11 -> -43565.041 | J11: =-'Cost of Revenue'!F12 -> -52449.805 | K11: =-'Cost of Revenue'!F13 -> -60801.484 | L11: =-'Cost of Revenue'!F14 -> -68652.061 | M11: =-'Cost of Revenue'!F15 -> -76031.604 | N11: =-SUM('Cost of Revenue'!F4:F15) -> -407700.42 | O11: =-SUM('Cost of Revenue'!F16:F27) -> -1821733.8 | P11: =-SUM('Cost of Revenue'!F28:F39) -> -3492910.7
A12: Gross profit | B12: ='Cost of Revenue'!H4 -> 31656.8 | C12: ='Cost of Revenue'!H5 -> 93070.992 | D12: ='Cost of Revenue'!H6 -> 150800.33 | E12: ='Cost of Revenue'!H7 -> 359581.25 | F12: ='Cost of Revenue'!H8 -> 608596.64 | G12: ='Cost of Revenue'!H9 -> 740917.11 | H12: ='Cost of Revenue'!H10 -> 939164.21 | I12: ='Cost of Revenue'!H11 -> 1199382.4 | J12: ='Cost of Revenue'!H12 -> 1443987.4 | K12: ='Cost of Revenue'!H13 -> 1673916.2 | L12: ='Cost of Revenue'!H14 -> 1890049.2 | M12: ='Cost of Revenue'!H15 -> 2093214.3 | N12: ='Cost of Revenue'!B41 -> 11224337 | O12: ='Cost of Revenue'!C41 -> 50153870 | P12: ='Cost of Revenue'!D41 -> 96162780
A13: Salaries | B13: =-'Operating Expenses'!B4 -> -1089000 | C13: =-'Operating Expenses'!B5 -> -1089000 | D13: =-'Operating Expenses'!B6 -> -1089000 | E13: =-'Operating Expenses'!B7 -> -1089000 | F13: =-'Operating Expenses'!B8 -> -1089000 | G13: =-'Operating Expenses'!B9 -> -1089000 | H13: =-'Operating Expenses'!B10 -> -2148000 | I13: =-'Operating Expenses'!B11 -> -2148000 | J13: =-'Operating Expenses'!B12 -> -2148000 | K13: =-'Operating Expenses'!B13 -> -2148000 | L13: =-'Operating Expenses'!B14 -> -2148000 | M13: =-'Operating Expenses'!B15 -> -2148000 | N13: =-SUM('Operating Expenses'!B4:B15) -> -19422000 | O13: =-SUM('Operating Expenses'!B16:B27) -> -33408000 | P13: =-SUM('Operating Expenses'!B28:B39) -> -41040000
A14: Marketing | B14: =-'Operating Expenses'!C4 -> -300000 | C14: =-'Operating Expenses'!C5 -> -300000 | D14: =-'Operating Expenses'!C6 -> -300000 | E14: =-'Operating Expenses'!C7 -> -800000 | F14: =-'Operating Expenses'!C8 -> -800000 | G14: =-'Operating Expenses'!C9 -> -800000 | H14: =-'Operating Expenses'!C10 -> -1500000 | I14: =-'Operating Expenses'!C11 -> -1500000 | J14: =-'Operating Expenses'!C12 -> -1500000 | K14: =-'Operating Expenses'!C13 -> -1500000 | L14: =-'Operating Expenses'!C14 -> -1500000 | M14: =-'Operating Expenses'!C15 -> -1500000 | N14: =-SUM('Operating Expenses'!C4:C15) -> -12300000 | O14: =-SUM('Operating Expenses'!C16:C27) -> -30000000 | P14: =-SUM('Operating Expenses'!C28:C39) -> -42000000
A15: Tech / software | B15: =-'Operating Expenses'!D4 -> -120000 | C15: =-'Operating Expenses'!D5 -> -120000 | D15: =-'Operating Expenses'!D6 -> -120000 | E15: =-'Operating Expenses'!D7 -> -120000 | F15: =-'Operating Expenses'!D8 -> -120000 | G15: =-'Operating Expenses'!D9 -> -120000 | H15: =-'Operating Expenses'!D10 -> -200000 | I15: =-'Operating Expenses'!D11 -> -200000 | J15: =-'Operating Expenses'!D12 -> -200000 | K15: =-'Operating Expenses'!D13 -> -200000 | L15: =-'Operating Expenses'!D14 -> -200000 | M15: =-'Operating Expenses'!D15 -> -200000 | N15: =-SUM('Operating Expenses'!D4:D15) -> -1920000 | O15: =-SUM('Operating Expenses'!D16:D27) -> -3120000 | P15: =-SUM('Operating Expenses'!D28:D39) -> -3840000
A16: G&A / legal | B16: =-'Operating Expenses'!E4 -> -150000 | C16: =-'Operating Expenses'!E5 -> -150000 | D16: =-'Operating Expenses'!E6 -> -150000 | E16: =-'Operating Expenses'!E7 -> -150000 | F16: =-'Operating Expenses'!E8 -> -150000 | G16: =-'Operating Expenses'!E9 -> -150000 | H16: =-'Operating Expenses'!E10 -> -250000 | I16: =-'Operating Expenses'!E11 -> -250000 | J16: =-'Operating Expenses'!E12 -> -250000 | K16: =-'Operating Expenses'!E13 -> -250000 | L16: =-'Operating Expenses'!E14 -> -250000 | M16: =-'Operating Expenses'!E15 -> -250000 | N16: =-SUM('Operating Expenses'!E4:E15) -> -2400000 | O16: =-SUM('Operating Expenses'!E16:E27) -> -3900000 | P16: =-SUM('Operating Expenses'!E28:E39) -> -4800000
A17: Contingency | B17: =-'Operating Expenses'!F4 -> -67950 | C17: =-'Operating Expenses'!F5 -> -67950 | D17: =-'Operating Expenses'!F6 -> -67950 | E17: =-'Operating Expenses'!F7 -> -67950 | F17: =-'Operating Expenses'!F8 -> -67950 | G17: =-'Operating Expenses'!F9 -> -67950 | H17: =-'Operating Expenses'!F10 -> -129900 | I17: =-'Operating Expenses'!F11 -> -129900 | J17: =-'Operating Expenses'!F12 -> -129900 | K17: =-'Operating Expenses'!F13 -> -129900 | L17: =-'Operating Expenses'!F14 -> -129900 | M17: =-'Operating Expenses'!F15 -> -129900 | N17: =-SUM('Operating Expenses'!F4:F15) -> -1187100 | O17: =-SUM('Operating Expenses'!F16:F27) -> -2021400 | P17: =-SUM('Operating Expenses'!F28:F39) -> -2484000
A18: EBITDA | B18: ='Operating Expenses'!J4 -> -1695293.2 | C18: ='Operating Expenses'!J5 -> -1633879 | D18: ='Operating Expenses'!J6 -> -1576149.7 | E18: ='Operating Expenses'!J7 -> -1867368.8 | F18: ='Operating Expenses'!J8 -> -1618353.4 | G18: ='Operating Expenses'!J9 -> -1486032.9 | H18: ='Operating Expenses'!J10 -> -3288735.8 | I18: ='Operating Expenses'!J11 -> -3028517.6 | J18: ='Operating Expenses'!J12 -> -2783912.6 | K18: ='Operating Expenses'!J13 -> -2553983.8 | L18: ='Operating Expenses'!J14 -> -2337850.8 | M18: ='Operating Expenses'!J15 -> -2134685.7 | N18: ='Operating Expenses'!B41 -> -26004763 | O18: ='Operating Expenses'!C41 -> -22295530 | P18: ='Operating Expenses'!D41 -> 1998779.6
A19: Depreciation | B19: =-8333 -> -8333 | C19: =-8333 -> -8333 | D19: =-8333 -> -8333 | E19: =-8333 -> -8333 | F19: =-8333 -> -8333 | G19: =-8333 -> -8333 | H19: =-8333 -> -8333 | I19: =-8333 -> -8333 | ... M19: =-8333 -> -8333 | N19: =-100000 -> -100000 | O19: =-100000 -> -100000 | P19: =-100000 -> -100000
A20: EBIT | B20: =B18+B19 -> -1703626.2 | C20: =C18+C19 -> -1642212 | D20: =D18+D19 -> -1584482.7 | E20: =E18+E19 -> -1875701.8 | F20: =F18+F19 -> -1626686.4 | G20: =G18+G19 -> -1494365.9 | H20: =H18+H19 -> -3297068.8 | I20: =I18+I19 -> -3036850.6 | ... P20: =P18+P19 -> 1898779.6
A21: Tax (nil until carry-forwards absorbed) | B21: =0 -> 0 | C21: =0 -> 0 | D21: =0 -> 0 | E21: =0 -> 0 | F21: =0 -> 0 | G21: =0 -> 0 | H21: =0 -> 0 | I21: =0 -> 0 | ... O21: =0 -> 0 | P21: =IF('Operating Expenses'!D41>0,-0.25*MAX(0,'Operating Expenses'!D41-100000-4500000),0) -> 0
A22: Net profit | B22: =B20+B21 -> -1703626.2 | C22: =C20+C21 -> -1642212 | D22: =D20+D21 -> -1584482.7 | E22: =E20+E21 -> -1875701.8 | F22: =F20+F21 -> -1626686.4 | G22: =G20+G21 -> -1494365.9 | H22: =H20+H21 -> -3297068.8 | I22: =I20+I21 -> -3036850.6 | ... P22: =P20+P21 -> 1898779.6
A24: GM % (Y1/Y2/Y3): | N24: =N12/N7 -> 0.79062937 | O24: =O12/O7 -> 0.79062937 | P24: =P12/P7 -> 0.79062937
A25: Note: Y3 tax formula assumes 25% on profit above accumulated losses of ~Rs45L absorbed; simplification flagged.

Sheet Cash Flow
A1: CASH FLOW - 36 MONTHS (Rs)
A3: Month | B3: Opening cash | C3: Investment in | D3: EBITDA | E3: Deferred-cash delta | F3: Capex | G3: Closing cash
A4: 1 | B4: 12500000 | C4: 0 | D4: ='Operating Expenses'!J4 -> -1695293.2 | E4: =Revenue!H4-IF(A4=1,0,Revenue!H3) -> 251020 | F4: 0 | G4: =B4+C4+D4+E4+F4 -> 11055727
A5: 2 | B5: =G4 -> 11055727 | C5: 0 | D5: ='Operating Expenses'!J5 -> -1633879 | E5: =Revenue!H5-IF(A5=1,0,Revenue!H4) -> 0 | F5: -150000 | G5: =B5+C5+D5+E5+F5 -> 9271847.8
A6: 3 | B6: =G5 -> 9271847.8 | C6: 0 | D6: ='Operating Expenses'!J6 -> -1576149.7 | E6: =Revenue!H6-IF(A6=1,0,Revenue!H5) -> 0 | F6: 0 | G6: =B6+C6+D6+E6+F6 -> 7695698.1
A7: 4 | B7: =G6 -> 7695698.1 | C7: 0 | D7: ='Operating Expenses'!J7 -> -1867368.8 | E7: =Revenue!H7-IF(A7=1,0,Revenue!H6) -> 1225216.7 | F7: 0 | G7: =B7+C7+D7+E7+F7 -> 7053546
A8: 5 | B8: =G7 -> 7053546 | C8: 0 | D8: ='Operating Expenses'!J8 -> -1618353.4 | E8: =Revenue!H8-IF(A8=1,0,Revenue!H7) -> -806850 | F8: 0 | G8: =B8+C8+D8+E8+F8 -> 4628342.7
A9: 6 | B9: =G8 -> 4628342.7 | C9: 0 | D9: ='Operating Expenses'!J9 -> -1486032.9 | E9: =Revenue!H9-IF(A9=1,0,Revenue!H8) -> 0 | F9: 0 | G9: =B9+C9+D9+E9+F9 -> 3142309.8
A10: 7 | B10: =G9 -> 3142309.8 | C10: 33000000 | D10: ='Operating Expenses'!J10 -> -3288735.8 | E10: =Revenue!H10-IF(A10=1,0,Revenue!H9) -> 585713.33 | F10: 0 | G10: =B10+C10+D10+E10+F10 -> 33439287
A11: 8 | B11: =G10 -> 33439287 | C11: 0 | D11: ='Operating Expenses'!J11 -> -3028517.6 | E11: =Revenue!H11-IF(A11=1,0,Revenue!H10) -> 0 | F11: -150000 | G11: =B11+C11+D11+E11+F11 -> 30260770
A12: 9 | B12: =G11 -> 30260770 | C12: 0 | D12: ='Operating Expenses'!J12 -> -2783912.6 | E12: =Revenue!H12-IF(A12=1,0,Revenue!H11) -> 0 | F12: 0 | G12: =B12+C12+D12+E12+F12 -> 27476857
A13: 10 | B13: =G12 -> 27476857 | C13: 0 | D13: ='Operating Expenses'!J13 -> -2553983.8 | E13: =Revenue!H13-IF(A13=1,0,Revenue!H12) -> 0 | F13: 0 | G13: =B13+C13+D13+E13+F13 -> 24922873
A14: 11 | B14: =G13 -> 24922873 | C14: 0 | D14: ='Operating Expenses'!J14 -> -2337850.8 | E14: =Revenue!H14-IF(A14=1,0,Revenue!H13) -> 0 | F14: 0 | G14: =B14+C14+D14+E14+F14 -> 22585022
A15: 12 | B15: =G14 -> 22585022 | C15: 0 | D15: ='Operating Expenses'!J15 -> -2134685.7 | E15: =Revenue!H15-IF(A15=1,0,Revenue!H14) -> 0 | F15: 0 | G15: =B15+C15+D15+E15+F15 -> 20450337
A16: 13 | B16: =G15 -> 20450337 | C16: 0 | D16: ='Operating Expenses'!J16 -> -2837640 | E16: =Revenue!H16-IF(A16=1,0,Revenue!H15) -> 836733.33 | F16: 0 | G16: =B16+C16+D16+E16+F16 -> 18449430
... A39: 36 | B39: =G38 -> 32787307 | C39: 0 | D39: ='Operating Expenses'!J39 -> 1889746.1 | E39: =Revenue!H39-IF(A39=1,0,Revenue!H38) -> 0 | F39: 0 | G39: =B39+C39+D39+E39+F39 -> 34677053
A41: Tranches: Rs1.25Cr at M1 (Scenario A: validate + build v1), Rs3.3Cr at M7 (Scenario B: launch), Rs3.3Cr at M19 (Scenario C: scale).
A42: Minimum-cash policy Rs40L; deferred-cash delta = annual-plan cash collected ahead of recognition.
A44: Minimum closing cash: | B44: =MIN(G4:G39) -> 3142309.8 | C44: Peak cumulative funding: | D44: =B4+SUM(C4:C39) -> 78500000

Sheet Unit Economics
A1: UNIT ECONOMICS PER CUSTOMER (Rs / month, base case)
A4: Total ARPU (subs + add-on) | B4: =Assumptions!B6+Assumptions!B7 -> 880
A5: AI cost | B5: =-Assumptions!B16 -> -70
A6: Human minutes | B6: =-Assumptions!B17 -> -45
A7: Support | B7: =-Assumptions!B18 -> -25
A8: Infra | B8: =-Assumptions!B20 -> -15
A9: Payment fees | B9: =-(Assumptions!B6+Assumptions!B7)*Assumptions!B19 -> -24.64
A10: Refunds | B10: =-(Assumptions!B6+Assumptions!B7)*Assumptions!B15 -> -22
A11: Contribution / user / month | B11: =SUM(B4:B10) -> 678.36
A12: Contribution margin % | B12: =B11/B4 -> 0.77086364
A13: Expected customer life (months) | B13: =1/Assumptions!B8 -> 16.666667
A14: LTV (contribution x life) | B14: =B11/Assumptions!B8 -> 11306
A15: CAC | B15: =Assumptions!B11 -> 3600
A16: LTV : CAC | B16: =B14/B15 -> 3.1405556
A17: CAC payback (months) | B17: =B15/B11 -> 5.3069167
A19: Plan-level contribution (Rs/mo):
A20: Plan | B20: Net ARPU | C20: Var. cost | D20: Contribution | E20: Margin
A21: NRI Premium | B21: =Pricing!H5 -> 1795.14 | C21: =-(Assumptions!B16+Assumptions!B17*3+Assumptions!B18+Assumptions!B20)-Pricing!H5*(Assumptions!B19+Assumptions!B15) -> -340.14242 | D21: =B21+C21 -> 1454.9976 | E21: =D21/B21 -> 0.81052039
A22: NRI Standard | B22: =Pricing!H4 -> 913.14 | C22: =-(Assumptions!B16+Assumptions!B18+Assumptions!B20)-Pricing!H4*(Assumptions!B19+Assumptions!B15) -> -158.39642 | D22: =B22+C22 -> 754.74358 | E22: =D22/B22 -> 0.82653654
A23: India Pragati | B23: =Pricing!H7 -> 677.58475 | C23: =-(Assumptions!B16+Assumptions!B17*1.5+Assumptions!B18+Assumptions!B20)-Pricing!H7*(Assumptions!B19+Assumptions!B15) -> -213.41199 | D23: =B23+C23 -> 464.17275 | E23: =D23/B23 -> 0.68504015
A24: India Aarambh | B24: =Pricing!H6 -> 338.60169 | C24: =-(Assumptions!B16+Assumptions!B18+Assumptions!B20)-Pricing!H6*(Assumptions!B19+Assumptions!B15) -> -127.94589 | D24: =B24+C24 -> 210.65581 | E24: =D24/B24 -> 0.62213453

Sheet Scenarios
A1: SCENARIOS - closed-form 36-month recursion per scenario
A3: Param | B3: Conservative | C3: Base | D3: Aggressive
A4: Monthly churn | B4: =Assumptions!B9 -> 0.075 | C4: =Assumptions!B8 -> 0.06 | D4: =Assumptions!B10 -> 0.045
A5: CAC (Rs) | B5: =Assumptions!B12 -> 4500 | C5: =Assumptions!B11 -> 3600 | D5: =Assumptions!B13 -> 3000
A6: Marketing multiplier | B6: 0.8 | C6: 1 | D6: 1.3
A7: ARPU multiplier | B7: 0.92 | C7: 1 | D7: 1.08
A9: Month | B9: Cons new | C9: Cons closing | D9: Base new | E9: Base closing | F9: Aggr new | G9: Aggr closing
A10: 1 | B10: ='Customer Growth'!B4*$B$6/$B$5*(1+Assumptions!$B$14)+IF(A10=4,Assumptions!$B$23,0) -> 59.733333 | C10: =B10 -> 59.733333 | D10: ='Customer Growth'!G4 -> 93.333333 | E10: ='Customer Growth'!K4 -> 93.333333 | F10: ='Customer Growth'!B4*$D$6/$D$5*(1+Assumptions!$B$14)+IF(A10=4,Assumptions!$B$23,0) -> 145.6 | G10: =F10 -> 145.6
A11: 2 | B11: ='Customer Growth'!B5*$B$6/$B$5*(1+Assumptions!$B$14)+IF(A11=4,Assumptions!$B$23,0) -> 59.733333 | C11: =C10*(1-$B$4)+B11 -> 114.98667 | D11: ='Customer Growth'!G5 -> 93.333333 | E11: ='Customer Growth'!K5 -> 181.06667 | F11: ='Customer Growth'!B5*$D$6/$D$5*(1+Assumptions!$B$14)+IF(A11=4,Assumptions!$B$23,0) -> 145.6 | G11: =G10*(1-$D$4)+F11 -> 284.648
A12: 3 | B12: ='Customer Growth'!B6*$B$6/$B$5*(1+Assumptions!$B$14)+IF(A12=4,Assumptions!$B$23,0) -> 59.733333 | C12: =C11*(1-$B$4)+B12 -> 166.096 | D12: ='Customer Growth'!G6 -> 93.333333 | E12: ='Customer Growth'!K6 -> 263.536 | F12: ='Customer Growth'!B6*$D$6/$D$5*(1+Assumptions!$B$14)+IF(A12=4,Assumptions!$B$23,0) -> 145.6 | G12: =G11*(1-$D$4)+F12 -> 417.43884
A13: 4 | B13: ='Customer Growth'!B7*$B$6/$B$5*(1+Assumptions!$B$14)+IF(A13=4,Assumptions!$B$23,0) -> 459.28889 | C13: =C12*(1-$B$4)+B13 -> 612.92769 | D13: ='Customer Growth'!G7 -> 548.88889 | E13: ='Customer Growth'!K7 -> 796.61273 | F13: ='Customer Growth'!B7*$D$6/$D$5*(1+Assumptions!$B$14)+IF(A13=4,Assumptions!$B$23,0) -> 688.26667 | G13: =G12*(1-$D$4)+F13 -> 1086.9208
A14: 5 | B14: ='Customer Growth'!B8*$B$6/$B$5*(1+Assumptions!$B$14)+IF(A14=4,Assumptions!$B$23,0) -> 159.28889 | C14: =C13*(1-$B$4)+B14 -> 726.247 | D14: ='Customer Growth'!G8 -> 248.88889 | E14: ='Customer Growth'!K8 -> 997.70485 | F14: ='Customer Growth'!B8*$D$6/$D$5*(1+Assumptions!$B$14)+IF(A14=4,Assumptions!$B$23,0) -> 388.26667 | G14: =G13*(1-$D$4)+F14 -> 1426.276
A15: 6 | B15: ='Customer Growth'!B9*$B$6/$B$5*(1+Assumptions!$B$14)+IF(A15=4,Assumptions!$B$23,0) -> 159.28889 | C15: =C14*(1-$B$4)+B15 -> 831.06736 | D15: ='Customer Growth'!G9 -> 248.88889 | E15: ='Customer Growth'!K9 -> 1186.7315 | F15: ='Customer Growth'!B9*$D$6/$D$5*(1+Assumptions!$B$14)+IF(A15=4,Assumptions!$B$23,0) -> 388.26667 | G15: =G14*(1-$D$4)+F15 -> 1750.3602
A16: 7 | B16: ='Customer Growth'!B10*$B$6/$B$5*(1+Assumptions!$B$14)+IF(A16=4,Assumptions!$B$23,0) -> 298.66667 | C16: =C15*(1-$B$4)+B16 -> 1067.404 | D16: ='Customer Growth'!G10 -> 466.66667 | E16: ='Customer Growth'!K10 -> 1582.1942 | F16: ='Customer Growth'!B10*$D$6/$D$5*(1+Assumptions!$B$14)+IF(A16=4,Assumptions!$B$23,0) -> 728 | G16: =G15*(1-$D$4)+F16 -> 2399.594
A17: 8 | B17: ='Customer Growth'!B11*$B$6/$B$5*(1+Assumptions!$B$14)+IF(A17=4,Assumptions!$B$23,0) -> 298.66667 | C17: =C16*(1-$B$4)+B17 -> 1286.0153 | D17: ='Customer Growth'!G11 -> 466.66667 | E17: ='Customer Growth'!K11 -> 1953.9292 | F17: ='Customer Growth'!B11*$D$6/$D$5*(1+Assumptions!$B$14)+IF(A17=4,Assumptions!$B$23,0) -> 728 | G17: =G16*(1-$D$4)+F17 -> 3019.6123
A18: 9 | B18: ='Customer Growth'!B12*$B$6/$B$5*(1+Assumptions!$B$14)+IF(A18=4,Assumptions!$B$23,0) -> 298.66667 | C18: =C17*(1-$B$4)+B18 -> 1488.2309 | D18: ='Customer Growth'!G12 -> 466.66667 | E18: ='Customer Growth'!K12 -> 2303.3602 | F18: ='Customer Growth'!B12*$D$6/$D$5*(1+Assumptions!$B$14)+IF(A18=4,Assumptions!$B$23,0) -> 728 | G18: =G17*(1-$D$4)+F18 -> 3611.7297
A19: 10 | B19: ='Customer Growth'!B13*$B$6/$B$5*(1+Assumptions!$B$14)+IF(A19=4,Assumptions!$B$23,0) -> 298.66667 | C19: =C18*(1-$B$4)+B19 -> 1675.2802 | D19: ='Customer Growth'!G13 -> 466.66667 | E19: ='Customer Growth'!K13 -> 2631.8252 | F19: ='Customer Growth'!B13*$D$6/$D$5*(1+Assumptions!$B$14)+IF(A19=4,Assumptions!$B$23,0) -> 728 | G19: =G18*(1-$D$4)+F19 -> 4177.2019
A20: 11 | B20: ='Customer Growth'!B14*$B$6/$B$5*(1+Assumptions!$B$14)+IF(A20=4,Assumptions!$B$23,0) -> 298.66667 | C20: =C19*(1-$B$4)+B20 -> 1848.3009 | D20: ='Customer Growth'!G14 -> 466.66667 | E20: ='Customer Growth'!K14 -> 2940.5824 | F20: ='Customer Growth'!B14*$D$6/$D$5*(1+Assumptions!$B$14)+IF(A20=4,Assumptions!$B$23,0) -> 728 | G20: =G19*(1-$D$4)+F20 -> 4717.2278
A21: 12 | B21: ='Customer Growth'!B15*$B$6/$B$5*(1+Assumptions!$B$14)+IF(A21=4,Assumptions!$B$23,0) -> 298.66667 | C21: =C20*(1-$B$4)+B21 -> 2008.345 | D21: ='Customer Growth'!G15 -> 466.66667 | E21: ='Customer Growth'!K15 -> 3230.8141 | F21: ='Customer Growth'!B15*$D$6/$D$5*(1+Assumptions!$B$14)+IF(A21=4,Assumptions!$B$23,0) -> 728 | G21: =G20*(1-$D$4)+F21 -> 5232.9526
A22: 13 | B22: ='Customer Growth'!B16*$B$6/$B$5*(1+Assumptions!$B$14)+IF(A22=4,Assumptions!$B$23,0) -> 497.77778 | C22: =C21*(1-$B$4)+B22 -> 2355.4969 | D22: ='Customer Growth'!G16 -> 777.77778 | E22: ='Customer Growth'!K16 -> 3816.3584 | F22: ='Customer Growth'!B16*$D$6/$D$5*(1+Assumptions!$B$14)+IF(A22=4,Assumptions!$B$23,0) -> 1213.3333 | G22: =G21*(1-$D$4)+F22 -> 6210.803
... A45: 36 | B45: ='Customer Growth'!B39*$B$6/$B$5*(1+Assumptions!$B$14)+IF(A45=4,Assumptions!$B$23,0) -> 696.88889 | C45: =C44*(1-$B$4)+B45 -> 7537.5471 | D45: ='Customer Growth'!G39 -> 1088.8889 | E45: ='Customer Growth'!K39 -> 14543.731 | F45: ='Customer Growth'!B39*$D$6/$D$5*(1+Assumptions!$B$14)+IF(A45=4,Assumptions!$B$23,0) -> 1698.6667 | G45: =G44*(1-$D$4)+F45 -> 24344.52
A47: Output | B47: Conservative | C47: Base | D47: Aggressive
A48: M36 customers | B48: =C45 -> 7537.5471 | C48: =E45 -> 14543.731 | D48: =G45 -> 24344.52
A49: Y3 revenue (Rs) | B49: =SUMPRODUCT((C34:C45+C33:C44)/2)*(Assumptions!B6+Assumptions!B7)*$B$7 -> 62046143 | C49: =Revenue!G41 -> 1.2162814e+08 | D49: =SUMPRODUCT((G34:G45+G33:G44)/2)*(Assumptions!B6+Assumptions!B7)*$D$7 -> 2.2639416e+08
A50: Y3 EBITDA approx (Rs) | B50: =B49*0.74-12*(3500000*$B$6+Headcount!D13+720000) -> -37365854 | C50: ='Operating Expenses'!D41 -> 1998779.6 | D50: =D49*0.74-12*(3500000*$D$6+Headcount!D13+720000) -> 63251677
A52: Conservative/aggressive P&L lines are closed-form approximations; base case ties to full engine.

Sheet Sensitivity
A1: SENSITIVITY - single-variable stresses vs base (equilibrium approximations)
A3: Stress | B3: Metric affected | C3: Base value | D3: Stressed value | E3: Impact
A4: Churn +25% (6.0% to 7.5%) | B4: M36 customers | C4: ='Customer Growth'!K39 -> 14543.731 | D4: ='Customer Growth'!G39/0.075*(1-(1-0.075)^36)*0.85 -> 11595.248 | E4: =D4-C4 -> -2948.4832
A5: CAC +25% (Rs3,600 to 4,500) | B5: M36 customers | C5: ='Customer Growth'!K39 -> 14543.731 | D5: =C5*0.8 -> 11634.985 | E5: =D5-C5 -> -2908.7462
A6: Conversion -25% | B6: New customers / month | C6: ='Customer Growth'!D15+'Customer Growth'!E15 -> 466.66667 | D6: =C6*0.75 -> 350 | E6: =D6-C6 -> -116.66667
A7: ARPU -15% | B7: Y3 revenue (Rs) | C7: =Revenue!G41 -> 1.2162814e+08 | D7: =C7*0.85 -> 1.0338392e+08 | E7: =D7-C7 -> -18244221
A8: AI cost x2 | B8: Gross margin % | C8: ='Cost of Revenue'!I39 -> 0.79062937 | D8: =C8-Assumptions!B16/(Assumptions!B6+Assumptions!B7) -> 0.71108392 | E8: =D8-C8 -> -0.079545455
A9: Growth delayed 6 months | B9: Peak funding need (Rs) | C9: ='Cash Flow'!D44 -> 78500000 | D9: =C9*1.17 -> 91845000 | E9: =D9-C9 -> 13345000
A10: Annual mix 40% (vs 60%) | B10: Deferred-cash benefit (Rs) | C10: =SUM(Revenue!H4:H39) -> 71343470 | D10: =C10*40/60 -> 47562313 | E10: =D10-C10 -> -23781157
A11: Refunds x2 (5%) | B11: Y3 net revenue (Rs) | C11: =Revenue!G41 -> 1.2162814e+08 | D11: =C11*(1-0.025) -> 1.1858744e+08 | E11: =D11-C11 -> -3040703.5
A13: TOP-3 PROFIT DRIVERS: (1) monthly churn, (2) ARPU/plan mix, (3) CAC - exactly what Gate-1 validation measures.
A14: Stressed values are closed-form approximations, not full re-runs; conservative scenario combines the first two.

Sheet Idea Comparison
A1: IDEA-WISE HIGH-LEVEL FINANCIALS (ranges; same assumption bases where fair)
A3: Metric | B3: Sitara (winner) | C3: Sahay (#2) | D3: KalaOS (#3) | E3: DharmaSetu (#4) | F3: Smriti (#5)
A4: MVP investment (Rs L) | B4: 60-100 | C4: 80-130 | D4: 60-100 | E4: 50-90 | F4: 60-90
A5: Full launch investment (Rs Cr) | B5: 3.5 | C5: 5.5-7 | D5: 2.5-3.5 | E5: 3-4 | F5: 3-4.5
A6: Price point | B6: Rs499-999 / $13-25 mo | C6: $49-299 mo | D6: Rs2,000-10,000 mo | E6: $10-17 mo + events | F6: $9-17 mo
A7: Gross margin % | B7: 72-78% | C7: 40-65% by tier | D7: 65-72% | E7: 55-70% blended | F7: 50-65% (print)
A8: Blended CAC (Rs) | B8: 3,000-4,500 | C8: 8,000-12,000 | D8: 8,000-15,000 (B2B) | E8: 4,000-6,000 | F8: 2,500-4,000
A9: Monthly churn | B9: 5-7.5% | C9: 2.5-4% + life events | D9: 2.5-3.5% logo | E9: 3-5% (annual-shaped) | F9: 3.5-5% + aging-out
A10: Break-even customers | B10: ~7,500-8,500 | C10: ~3,500-4,500 | D10: ~1,600-2,000 studios | E10: ~9,000-11,000 members | F10: ~11,000-14,000
A11: Break-even month (base) | B11: ~M27 | C11: ~M30-34 | D11: ~M22-26 | E11: ~M28-34 | F11: ~M30-36
A12: Y1 revenue (Rs Cr) | B12: 1.3-1.8 | C12: 1.5-2.5 | D12: 0.8-1.4 | E12: 0.9-1.6 | F12: 0.7-1.2
A13: Y3 revenue (Rs Cr) | B13: 11-17 | C13: 16-22 | D13: 9-12 | E13: 7-11 | F13: 6-10
A14: Y3 EBITDA (Rs Cr) | B14: 0.8-1.8 | C14: (1)-1.5 | D14: 1.2-2.2 | E14: 0.3-1.2 | F14: (0.5)-0.8
... A16: Risk-adjusted score /10 | B16: 8.1 | C16: 8.0 | D16: 7.6 | E16: 7.4 | F16: 7.1
A18: Ranges reflect low confidence bounds; no false precision. Sahay/KalaOS/DharmaSetu/Smriti models are top-down
A19: scaled from the same ARPU/churn/CAC logic; Sitara ties to the full bottom-up engine.

Sheet Investment Returns
A1: RETURNS BY INVESTMENT LEVEL (management estimates; capital does NOT buy retention)
A3: Level | B3: Rs50 L | C3: Rs1 Cr | D3: Rs2.5 Cr | E3: Rs5 Cr | F3: Rs10 Cr
A4: What it buys | B4: Concierge validation only (no product) | C4: Validation + MVP + founding 500 | D4: MVP + 18-mo launch (Scenario A+partial B) | E4: Full A+B+early C | F4: Full staged plan + India tier + rituals
A5: Team (FTE) | B5: 2-3 | C5: 4-5 | D5: 8-9 | E5: 12-15 | F5: 20-24
A6: Runway (months) | B6: 6-7 | C6: 9-10 | D6: 10-14 | E6: 20-24 | F6: 30-36
A7: Marketing budget (Rs) | B7: 8 L | C7: 25 L | D7: 1.05 Cr | E7: 2.4 Cr | F7: 5.6 Cr
A8: Target paying customers | B8: 50 pilot + 250 founding | C8: 500-800 | D8: 3,000-3,500 | E8: 8,000-9,500 | F8: 16,000-19,000
A9: Exit ARR (Rs Cr) | B9: 0.25 | C9: 0.7-0.9 | D9: 3.0-3.6 | E9: 8.5-10 | F9: 17-20
A10: Break-even | B10: n/a (validation) | C10: n/a | D10: path visible M18 | E10: ~M27 | F10: ~M26-28
A11: 3-yr cumulative revenue (Rs Cr) | B11: n/a | C11: 2-3 | D11: 8-10 | E11: 18-23 | F11: 20-26
A12: 3-yr cumulative EBITDA (Rs Cr) | B12: (0.5) | C12: (0.9)-(1.1) | D12: (2.5)-(3.2) | E12: (3.5)-(4.2) | F12: (3.2)-(4.0)
A13: Cash returned / retained | B13: Learning + stop-loss | C13: Brand + panel + cohort data | D13: Deferred-rev cushion ~Rs60L | E13: Rs1-2 Cr closing cash | F13: Rs1.5-3 Cr closing cash
A14: ROI shape | B14: Option value only | C14: Option value | D14: Series-A readiness | E14: 2-4x revenue multiple potential | F14: 3-5x potential IF churn<=6%
... A16: Milestone before next funding | B16: M2 renewal >=60% | C16: 500 founding, CAC<Rs4,000 | D16: Churn<=6%, NPS>=55 | E16: Cohort audit | F16: Category leadership metrics
A18: Higher investment does NOT generate proportionate returns: retention gates, CAC inflation at scale,
A19: and category ceilings bind every level. The staged plan (Rs65L -> Rs2.85Cr -> Rs4.5Cr) is the recommended path.

Sheet Dashboard
A1: DASHBOARD - KEY OUTPUTS (all linked; recalc after edits)
A3: Paying customers M12 | B3: ='Customer Growth'!K15 -> 3230.8141
A4: Paying customers M24 | B4: ='Customer Growth'!K27 -> 8551.5852
A5: Paying customers M36 | B5: ='Customer Growth'!K39 -> 14543.731
A6: Revenue Y1 (Rs) | B6: =Revenue!C41 -> 14196711
A7: Revenue Y2 (Rs) | B7: =Revenue!E41 -> 63435374
A8: Revenue Y3 (Rs) | B8: =Revenue!G41 -> 1.2162814e+08
A9: Gross margin Y3 | B9: ='P&L'!P24 -> 0.79062937
A10: EBITDA Y1 (Rs) | B10: ='Operating Expenses'!B41 -> -26004763
A11: EBITDA Y2 (Rs) | B11: ='Operating Expenses'!C41 -> -22295530
A12: EBITDA Y3 (Rs) | B12: ='Operating Expenses'!D41 -> 1998779.6
A13: LTV (Rs) | B13: ='Unit Economics'!B14 -> 11306
A14: CAC (Rs) | B14: ='Unit Economics'!B15 -> 3600
A15: LTV:CAC | B15: ='Unit Economics'!B16 -> 3.1405556
A16: CAC payback (months) | B16: ='Unit Economics'!B17 -> 5.3069167
A17: Peak cumulative funding (Rs) | B17: ='Cash Flow'!D44 -> 78500000
A18: Minimum cash balance (Rs) | B18: ='Cash Flow'!B44 -> 3142309.8
A19: Closing cash M36 (Rs) | B19: ='Cash Flow'!G39 -> 34677053
